grab_favicon/__init__.py
grab_favicon/grabber.py
grab_favicon-1.0.9.dist-info/METADATA
grab_favicon-1.0.9.dist-info/WHEEL
grab_favicon-1.0.9.dist-info/top_level.txt
grab_favicon-1.0.9.dist-info/RECORD
