Metadata-Version: 2.1
Name: grab_favicon
Version: 1.0.9
Summary: Python functions to download favicons using internal google api
Author: Emilio Mendoza
Author-email: emen3998@gmail.com
Keywords: python,favicon,downloader,grabber
Classifier: Development Status :: 5 - Production/Stable
Classifier: Intended Audience :: Developers
Classifier: Programming Language :: Python :: 3
Classifier: Operating System :: Unix
Classifier: Operating System :: MacOS :: MacOS X
Classifier: Operating System :: Microsoft :: Windows
